funk_lines/__init__.py
funk_lines/__main__.py
funk_lines/cli.py
funk_lines/core/__init__.py
funk_lines/core/analysers/__init__.py
funk_lines/core/analysers/base_analyser.py
funk_lines/core/analysers/dir_analyser.py
funk_lines/core/analysers/file_analyser.py
funk_lines/core/ast_processors/__init__.py
funk_lines/core/ast_processors/base.py
funk_lines/core/ast_processors/function_processor.py
funk_lines/core/main.py
funk_lines/core/results.py
funk_lines/py.typed
funk_lines-0.1.0.dist-info/entry_points.txt
funk_lines-0.1.0.dist-info/WHEEL
funk_lines-0.1.0.dist-info/METADATA
funk_lines-0.1.0.dist-info/RECORD
