Metadata-Version: 2.1
Name: funk-lines
Version: 0.1.0
Summary: Funk Lines
Home-page: https://github.com/federicober/funk-lines
License: MIT
Author: Federico Oberndorfer
Author-email: federico.ober@hotmail.com
Requires-Python: >=3.10.2,<4.0.0
Classifier: License :: OSI Approved :: MIT License
Classifier: Programming Language :: Python :: 3
Classifier: Programming Language :: Python :: 3.10
Requires-Dist: rich (>=11.1.0,<12.0.0)
Requires-Dist: typer (>=0.4.0,<0.5.0)
Project-URL: Changelog, https://github.com/federicober/funk-lines/releases
Project-URL: Documentation, https://funk-lines.readthedocs.io
Project-URL: Repository, https://github.com/federicober/funk-lines
